Mylib049/__init__.py
Mylib049-0.1.dist-info/LICENSE.txt
Mylib049-0.1.dist-info/METADATA
Mylib049-0.1.dist-info/WHEEL
Mylib049-0.1.dist-info/top_level.txt
Mylib049-0.1.dist-info/RECORD
