Metadata-Version: 2.1
Name: Mylib049
Version: 0.1
Summary: accept string and return mpdified version of it
Author: Tejas
Author-email: tejasjoshi758@gmail.com
Classifier: Programming Language :: Python :: 3
Classifier: License :: OSI Approved :: MIT License
Classifier: Operating System :: OS Independent
License-File: LICENSE.txt
